{
  "info": {
    "video_id": "JIRGw8w1sBQ",
    "title": "Зачем в СССР кирпич ложили в бачок унитаза? #история #shorts",
    "description": "",
    "duration": 33,
    "channel": "История за 30 секунд",
    "channel_id": "UCUZH5SMWh94y26P3zGfihVQ",
    "upload_date": "20251011",
    "view_count": 5431415,
    "like_count": 34659,
    "categories": [
      "People & Blogs"
    ],
    "tags": []
  },
  "chapters": [],
  "transcript": {
    "language": "ru",
    "type": "generated",
    "segments": [
      {
        "start": 0.199,
        "duration": 0.0,
        "text": "Зачем<00:00:00.560><c> в</c><00:00:00.719><c> СССР</c><00:00:01.319><c> кирпич</c><00:00:01.800><c> ложили</c><00:00:02.120><c> в</c><00:00:02.320><c> бачок</c>"
      },
      {
        "start": 2.75,
        "duration": 0.0,
        "text": "Зачем в СССР кирпич ложили в бачок"
      },
      {
        "start": 2.76,
        "duration": 0.0,
        "text": "Зачем в СССР кирпич ложили в бачок унитаза?<00:00:03.800><c> Сегодня</c><00:00:04.240><c> говорят,</c><00:00:04.920><c> для</c><00:00:05.160><c> экономии</c>"
      },
      {
        "start": 5.789,
        "duration": 0.0,
        "text": "унитаза? Сегодня говорят, для экономии"
      },
      {
        "start": 5.799,
        "duration": 0.0,
        "text": "унитаза? Сегодня говорят, для экономии воды.<00:00:06.399><c> Но</c><00:00:06.560><c> нет,</c><00:00:07.080><c> тогда</c><00:00:07.439><c> ведь</c><00:00:07.640><c> никто</c><00:00:07.860><c> [музыка]</c>"
      },
      {
        "start": 7.909,
        "duration": 0.0,
        "text": "воды. Но нет, тогда ведь никто [музыка]"
      },
      {
        "start": 7.919,
        "duration": 0.0,
        "text": "воды. Но нет, тогда ведь никто [музыка] не<00:00:08.120><c> платил</c><00:00:08.559><c> за</c><00:00:08.719><c> воду.</c><00:00:09.200><c> Счётчиков</c><00:00:09.840><c> не</c><00:00:10.000><c> было,</c><00:00:10.480><c> а</c>"
      },
      {
        "start": 10.669,
        "duration": 0.0,
        "text": "не платил за воду. Счётчиков не было, а"
      },
      {
        "start": 10.679,
        "duration": 0.0,
        "text": "не платил за воду. Счётчиков не было, а кирпич<00:00:11.080><c> лежал</c><00:00:11.480><c> в</c><00:00:11.599><c> бочке</c><00:00:12.080><c> у</c><00:00:12.280><c> каждого</c><00:00:12.719><c> второго.</c>"
      },
      {
        "start": 13.629,
        "duration": 0.0,
        "text": "кирпич лежал в бочке у каждого второго."
      },
      {
        "start": 13.639,
        "duration": 0.0,
        "text": "кирпич лежал в бочке у каждого второго. Вода<00:00:13.920><c> текла</c><00:00:14.320><c> слабо,</c><00:00:14.960><c> особенно</c><00:00:15.360><c> в</c><00:00:15.480><c> старых</c>"
      },
      {
        "start": 15.829,
        "duration": 0.0,
        "text": "Вода текла слабо, особенно в старых"
      },
      {
        "start": 15.839,
        "duration": 0.0,
        "text": "Вода текла слабо, особенно в старых домах<00:00:16.160><c> и</c><00:00:16.320><c> на</c><00:00:16.440><c> верхних</c><00:00:16.800><c> этажах.</c><00:00:17.680><c> После</c><00:00:18.000><c> каждого</c>"
      },
      {
        "start": 18.39,
        "duration": 0.0,
        "text": "домах и на верхних этажах. После каждого"
      },
      {
        "start": 18.4,
        "duration": 0.0,
        "text": "домах и на верхних этажах. После каждого смыва<00:00:18.840><c> приходилось</c><00:00:19.439><c> ждать</c><00:00:19.800><c> целую</c><00:00:20.320><c> вечность,</c>"
      },
      {
        "start": 21.029,
        "duration": 0.0,
        "text": "смыва приходилось ждать целую вечность,"
      },
      {
        "start": 21.039,
        "duration": 0.0,
        "text": "смыва приходилось ждать целую вечность, а<00:00:21.160><c> утром</c><00:00:21.519><c> вся</c><00:00:21.800><c> семья</c><00:00:22.240><c> стояла</c><00:00:22.720><c> в</c><00:00:22.840><c> очереди.</c>"
      },
      {
        "start": 23.71,
        "duration": 0.0,
        "text": "а утром вся семья стояла в очереди."
      },
      {
        "start": 23.72,
        "duration": 0.0,
        "text": "а утром вся семья стояла в очереди. Тогда<00:00:23.960><c> и</c><00:00:24.160><c> придумали</c><00:00:24.960><c> положить</c><00:00:25.400><c> в</c><00:00:25.560><c> бачок</c>"
      },
      {
        "start": 26.029,
        "duration": 0.0,
        "text": "Тогда и придумали положить в бачок"
      },
      {
        "start": 26.039,
        "duration": 0.0,
        "text": "Тогда и придумали положить в бачок кирпич.<00:00:26.760><c> Он</c><00:00:26.920><c> занимал</c><00:00:27.400><c> часть</c><00:00:27.760><c> объёма</c><00:00:28.240><c> и</c>"
      },
      {
        "start": 28.39,
        "duration": 0.0,
        "text": "кирпич. Он занимал часть объёма и"
      },
      {
        "start": 28.4,
        "duration": 0.0,
        "text": "кирпич. Он занимал часть объёма и вытеснял<00:00:29.119><c> воду.</c><00:00:29.800><c> Меньше</c><00:00:30.130><c> [музыка]</c><00:00:30.199><c> воды,</c>"
      },
      {
        "start": 30.83,
        "duration": 0.0,
        "text": "вытеснял воду. Меньше [музыка] воды,"
      },
      {
        "start": 30.84,
        "duration": 0.0,
        "text": "вытеснял воду. Меньше [музыка] воды, быстрее<00:00:31.359><c> бачок</c><00:00:31.759><c> наполнялся.</c>"
      }
    ],
    "source": "yt_dlp",
    "raw_format": "vtt"
  },
  "full_text": "Зачем<00:00:00.560><c> в</c><00:00:00.719><c> СССР</c><00:00:01.319><c> кирпич</c><00:00:01.800><c> ложили</c><00:00:02.120><c> в</c><00:00:02.320><c> бачок</c> Зачем в СССР кирпич ложили в бачок Зачем в СССР кирпич ложили в бачок унитаза?<00:00:03.800><c> Сегодня</c><00:00:04.240><c> говорят,</c><00:00:04.920><c> для</c><00:00:05.160><c> экономии</c> унитаза? Сегодня говорят, для экономии унитаза? Сегодня говорят, для экономии воды.<00:00:06.399><c> Но</c><00:00:06.560><c> нет,</c><00:00:07.080><c> тогда</c><00:00:07.439><c> ведь</c><00:00:07.640><c> никто</c><00:00:07.860><c> [музыка]</c> воды. Но нет, тогда ведь никто [музыка] воды. Но нет, тогда ведь никто [музыка] не<00:00:08.120><c> платил</c><00:00:08.559><c> за</c><00:00:08.719><c> воду.</c><00:00:09.200><c> Счётчиков</c><00:00:09.840><c> не</c><00:00:10.000><c> было,</c><00:00:10.480><c> а</c> не платил за воду. Счётчиков не было, а не платил за воду. Счётчиков не было, а кирпич<00:00:11.080><c> лежал</c><00:00:11.480><c> в</c><00:00:11.599><c> бочке</c><00:00:12.080><c> у</c><00:00:12.280><c> каждого</c><00:00:12.719><c> второго.</c> кирпич лежал в бочке у каждого второго. кирпич лежал в бочке у каждого второго. Вода<00:00:13.920><c> текла</c><00:00:14.320><c> слабо,</c><00:00:14.960><c> особенно</c><00:00:15.360><c> в</c><00:00:15.480><c> старых</c> Вода текла слабо, особенно в старых Вода текла слабо, особенно в старых домах<00:00:16.160><c> и</c><00:00:16.320><c> на</c><00:00:16.440><c> верхних</c><00:00:16.800><c> этажах.</c><00:00:17.680><c> После</c><00:00:18.000><c> каждого</c> домах и на верхних этажах. После каждого домах и на верхних этажах. После каждого смыва<00:00:18.840><c> приходилось</c><00:00:19.439><c> ждать</c><00:00:19.800><c> целую</c><00:00:20.320><c> вечность,</c> смыва приходилось ждать целую вечность, смыва приходилось ждать целую вечность, а<00:00:21.160><c> утром</c><00:00:21.519><c> вся</c><00:00:21.800><c> семья</c><00:00:22.240><c> стояла</c><00:00:22.720><c> в</c><00:00:22.840><c> очереди.</c> а утром вся семья стояла в очереди. а утром вся семья стояла в очереди. Тогда<00:00:23.960><c> и</c><00:00:24.160><c> придумали</c><00:00:24.960><c> положить</c><00:00:25.400><c> в</c><00:00:25.560><c> бачок</c> Тогда и придумали положить в бачок Тогда и придумали положить в бачок кирпич.<00:00:26.760><c> Он</c><00:00:26.920><c> занимал</c><00:00:27.400><c> часть</c><00:00:27.760><c> объёма</c><00:00:28.240><c> и</c> кирпич. Он занимал часть объёма и кирпич. Он занимал часть объёма и вытеснял<00:00:29.119><c> воду.</c><00:00:29.800><c> Меньше</c><00:00:30.130><c> [музыка]</c><00:00:30.199><c> воды,</c> вытеснял воду. Меньше [музыка] воды, вытеснял воду. Меньше [музыка] воды, быстрее<00:00:31.359><c> бачок</c><00:00:31.759><c> наполнялся.</c>"
}